{"sequence": [{"type": "v", "data": {"amp": 0.116, "freq": 133.5, "form": "sine", "dur": 26.06}}, {"type": "v", "data": {"amp": 0.261, "freq": 129.6, "form": "sine", "dur": 28.94}}, {"type": "v", "data": {"amp": 0.323, "freq": 129.5, "form": "sine", "dur": 25.25}}, {"type": "v", "data": {"amp": 0.455, "freq": 135.8, "form": "sine", "dur": 26.62}}, {"type": "v", "data": {"amp": 0.542, "freq": 134.9, "form": "sine", "dur": 25.75}}, {"type": "v", "data": {"amp": 0.588, "freq": 133.6, "form": "sine", "dur": 25.06}}, {"type": "v", "data": {"amp": 0.193, "freq": 134.1, "form": "sine", "dur": 25.31}}, {"type": "v", "data": {"amp": 0.174, "freq": 138.1, "form": "sine", "dur": 28.81}}, {"type": "v", "data": {"amp": 0.265, "freq": 143.4, "form": "sine", "dur": 26.38}}, {"type": "v", "data": {"amp": 0.376, "freq": 132.8, "form": "sine", "dur": 25.94}}, {"type": "v", "data": {"amp": 0.446, "freq": 138.9, "form": "sine", "dur": 26.25}}, {"type": "v", "data": {"amp": 0.601, "freq": 138.4, "form": "sine", "dur": 25.69}}, {"type": "v", "data": {"amp": 0.514, "freq": 132.9, "form": "sine", "dur": 26.88}}, {"type": "v", "data": {"amp": 0.094, "freq": 129.6, "form": "sine", "dur": 26.94}}, {"type": "v", "data": {"amp": 0.244, "freq": 120.5, "form": "sine", "dur": 32.19}}, {"type": "v", "data": {"amp": 0.304, "freq": 127.0, "form": "sine", "dur": 28.44}}, {"type": "v", "data": {"amp": 0.444, "freq": 131.4, "form": "sine", "dur": 27.19}}, {"type": "v", "data": {"amp": 0.555, "freq": 133.4, "form": "sine", "dur": 27.38}}, {"type": "v", "data": {"amp": 0.584, "freq": 133.2, "form": "sine", "dur": 25.06}}, {"type": "v", "data": {"amp": 0.192, "freq": 133.1, "form": "sine", "dur": 25.38}}, {"type": "v", "data": {"amp": 0.171, "freq": 144.6, "form": "sine", "dur": 28.75}}, {"type": "v", "data": {"amp": 0.262, "freq": 166.4, "form": "sine", "dur": 26.44}}, {"type": "v", "data": {"amp": 0.375, "freq": 137.0, "form": "sine", "dur": 25.88}}, {"type": "v", "data": {"amp": 0.444, "freq": 132.4, "form": "sine", "dur": 26.31}}, {"type": "v", "data": {"amp": 0.593, "freq": 133.5, "form": "sine", "dur": 25.69}}, {"type": "v", "data": {"amp": 0.512, "freq": 133.3, "form": "sine", "dur": 26.88}}, {"type": "v", "data": {"amp": 0.096, "freq": 129.5, "form": "sine", "dur": 26.94}}, {"type": "v", "data": {"amp": 0.245, "freq": 120.0, "form": "sine", "dur": 32.19}}, {"type": "v", "data": {"amp": 0.304, "freq": 126.4, "form": "sine", "dur": 28.38}}, {"type": "v", "data": {"amp": 0.444, "freq": 131.5, "form": "sine", "dur": 27.19}}, {"type": "v", "data": {"amp": 0.555, "freq": 133.9, "form": "sine", "dur": 27.44}}, {"type": "v", "data": {"amp": 0.592, "freq": 133.8, "form": "sine", "dur": 25.06}}, {"type": "v", "data": {"amp": 0.193, "freq": 133.6, "form": "sine", "dur": 25.38}}, {"type": "v", "data": {"amp": 0.172, "freq": 162.5, "form": "sine", "dur": 28.75}}, {"type": "v", "data": {"amp": 0.263, "freq": 207.7, "form": "sine", "dur": 26.38}}, {"type": "v", "data": {"amp": 0.375, "freq": 146.1, "form": "sine", "dur": 25.94}}, {"type": "v", "data": {"amp": 0.447, "freq": 160.0, "form": "sine", "dur": 26.25}}, {"type": "v", "data": {"amp": 0.594, "freq": 157.3, "form": "sine", "dur": 25.75}}, {"type": "v", "data": {"amp": 0.529, "freq": 159.3, "form": "sine", "dur": 25.12}}, {"type": "p", "data": {"dur": 179.125}}]}