{"sequence": [{"type": "v", "data": {"amp": 0.1, "freq": 247, "form": "sine", "dur": 89}}, {"type": "v", "data": {"amp": 0.25, "freq": 247, "form": "sine", "dur": 44}}, {"type": "v", "data": {"amp": 0.06, "freq": 187, "form": "sine", "dur": 93}}, {"type": "v", "data": {"amp": 0.64, "freq": 171, "form": "sine", "dur": 28}}, {"type": "v", "data": {"amp": 0.59, "freq": 170, "form": "sine", "dur": 65}}, {"type": "v", "data": {"amp": 0.05, "freq": 116, "form": "sine", "dur": 46}}, {"type": "v", "data": {"amp": 0.94, "freq": 72, "form": "sine", "dur": 31}}, {"type": "v", "data": {"amp": 0.87, "freq": 72, "form": "sine", "dur": 70}}, {"type": "v", "data": {"amp": 0.57, "freq": 72, "form": "sine", "dur": 28}}, {"type": "v", "data": {"amp": 0.12, "freq": 72, "form": "sine", "dur": 108}}, {"type": "v", "data": {"amp": 0.88, "freq": 72, "form": "sine", "dur": 92}}, {"type": "v", "data": {"amp": 0.02, "freq": 73, "form": "sine", "dur": 38}}]}