{"sequence": [{"type": "v", "data": {"amp": 0.9, "freq": 155, "form": "sine", "dur": 52}}, {"type": "v", "data": {"amp": 0.69, "freq": 144, "form": "sine", "dur": 50}}, {"type": "v", "data": {"amp": 0.49, "freq": 125, "form": "sine", "dur": 51}}, {"type": "v", "data": {"amp": 0.29, "freq": 117, "form": "sine", "dur": 51}}, {"type": "v", "data": {"amp": 0.14, "freq": 155, "form": "sine", "dur": 47}}, {"type": "v", "data": {"amp": 0.9, "freq": 155, "form": "sine", "dur": 50}}, {"type": "v", "data": {"amp": 0.69, "freq": 143, "form": "sine", "dur": 50}}, {"type": "v", "data": {"amp": 0.49, "freq": 125, "form": "sine", "dur": 51}}, {"type": "v", "data": {"amp": 0.29, "freq": 129, "form": "sine", "dur": 51}}, {"type": "v", "data": {"amp": 0.14, "freq": 158, "form": "sine", "dur": 47}}, {"type": "v", "data": {"amp": 0.9, "freq": 155, "form": "sine", "dur": 50}}, {"type": "v", "data": {"amp": 0.69, "freq": 142, "form": "sine", "dur": 50}}, {"type": "v", "data": {"amp": 0.49, "freq": 118, "form": "sine", "dur": 51}}, {"type": "v", "data": {"amp": 0.29, "freq": 85, "form": "sine", "dur": 51}}, {"type": "v", "data": {"amp": 0.18, "freq": 76, "form": "sine", "dur": 49}}, {"type": "v", "data": {"amp": 1.0, "freq": 78, "form": "sine", "dur": 747}}, {"type": "v", "data": {"amp": 0.93, "freq": 99, "form": "sine", "dur": 25}}, {"type": "v", "data": {"amp": 0.8, "freq": 142, "form": "sine", "dur": 52}}, {"type": "v", "data": {"amp": 0.59, "freq": 128, "form": "sine", "dur": 53}}, {"type": "v", "data": {"amp": 0.37, "freq": 96, "form": "sine", "dur": 56}}, {"type": "v", "data": {"amp": 0.16, "freq": 77, "form": "sine", "dur": 52}}, {"type": "v", "data": {"amp": 0.72, "freq": 75, "form": "sine", "dur": 28}}, {"type": "v", "data": {"amp": 1.0, "freq": 75, "form": "sine", "dur": 233}}]}